LICENSE
MANIFEST.in
README.md
requirements.txt
setup.cfg
setup.py
groupenc/__init__.py
groupenc/__main__.py
groupenc/config.py
groupenc/helpers.py
groupenc/identity.py
groupenc/vault.py
groupenc.egg-info/PKG-INFO
groupenc.egg-info/SOURCES.txt
groupenc.egg-info/dependency_links.txt
groupenc.egg-info/entry_points.txt
groupenc.egg-info/requires.txt
groupenc.egg-info/top_level.txt
groupenc.egg-info/zip-safe
tests/test_identity.py
tests/test_vault.py