Metadata-Version: 2.1
Name: groupenc
Version: 0.3.0
Summary: groupenc: Group Encryption Utilities
Home-page: http://github.com/guilt/groupenc
Author: Karthik Kumar Viswanathan
Author-email: karthikkumar@gmail.com
License: MIT
Keywords: groupenc encryption group vault offline
Classifier: Topic :: Software Development :: Libraries
Classifier: Programming Language :: Python :: 2.7
Classifier: Programming Language :: Python :: 3.6
Classifier: Programming Language :: Python :: 3.7
Classifier: Programming Language :: Python :: 3.8
Classifier: Programming Language :: Python :: 3.9
License-File: LICENSE
Requires-Dist: setuptools
Requires-Dist: pycryptodome>=3.9.0
Requires-Dist: colorama
